loopsleuth/__init__.py
loopsleuth/__main__.py
loopsleuth/loopsleuth_bin
loopsleuth/models.py
loopsleuth/py.typed
loopsleuth.libs/libgomp-e985bcbb.so.1.0.0
loopsleuth-0.1.0.dist-info/METADATA
loopsleuth-0.1.0.dist-info/WHEEL
loopsleuth-0.1.0.dist-info/entry_points.txt
loopsleuth-0.1.0.dist-info/top_level.txt
loopsleuth-0.1.0.dist-info/RECORD
loopsleuth-0.1.0.dist-info/licenses/LICENSE
loopsleuth-0.1.0.dist-info/sboms/auditwheel.cdx.json
