Metadata-Version: 2.4
Name: loopsleuth
Version: 0.1.0
Summary: AI-powered Python performance analyzer that detects algorithmic bottlenecks
Author-email: Tarek Ziadé <tarek@ziade.org>
License: MIT
Project-URL: Homepage, https://github.com/tarekziade/loopsleuth
Project-URL: Repository, https://github.com/tarekziade/loopsleuth
Keywords: performance,profiling,optimization,static-analysis,code-quality
Classifier: Development Status :: 4 - Beta
Classifier: Intended Audience :: Developers
Classifier: Topic :: Software Development :: Quality Assurance
Classifier: Topic :: Software Development :: Testing
Classifier: License :: OSI Approved :: MIT License
Classifier: Programming Language :: Python :: 3
Classifier: Programming Language :: Python :: 3.10
Classifier: Programming Language :: Python :: 3.11
Classifier: Programming Language :: Python :: 3.12
Classifier: Programming Language :: Python :: 3.13
Classifier: Programming Language :: Python :: 3.14
Classifier: Programming Language :: Rust
Requires-Python: >=3.10
License-File: LICENSE
Provides-Extra: download
Requires-Dist: huggingface_hub>=0.20.0; extra == "download"
Dynamic: license-file
